kedi/__init__.py
kedi-0.1.0.dist-info/METADATA
kedi-0.1.0.dist-info/WHEEL
kedi-0.1.0.dist-info/top_level.txt
kedi-0.1.0.dist-info/RECORD
