Metadata-Version: 2.4
Name: kedi
Version: 0.1.0
Summary: kedi is a Python package.
Author: fswair
Classifier: Programming Language :: Python :: 3
Classifier: License :: OSI Approved :: MIT License
Classifier: Operating System :: OS Independent
Dynamic: author
Dynamic: classifier
Dynamic: summary
